catacomb/__init__.py
catacomb/auth.py
catacomb/cli.py
catacomb/common.py
catacomb/docker_logic.py
catacomb/local.py
catacomb/proxy.py
catacomb/static.py
catacomb/systems.py
catacomb/typing.py
catacomb_ai-0.1.29.dist-info/METADATA
catacomb_ai-0.1.29.dist-info/WHEEL
catacomb_ai-0.1.29.dist-info/entry_points.txt
catacomb_ai-0.1.29.dist-info/top_level.txt
catacomb_ai-0.1.29.dist-info/RECORD
