Metadata-Version: 2.1
Name: catacomb-ai
Version: 0.1.29
Summary: Build tools for Catacomb's model hosting suite.
Home-page: UNKNOWN
Author: UNKNOWN
Author-email: UNKNOWN
License: UNKNOWN
Platform: UNKNOWN
Requires-Dist: Click
Requires-Dist: docker
Requires-Dist: requests
Requires-Dist: pyyaml
Requires-Dist: flask-cors
Requires-Dist: flask
Requires-Dist: websockets
Requires-Dist: nest-asyncio
